pybpmn/__init__.py
pybpmn/constants.py
pybpmn/dataset.py
pybpmn/parser.py
pybpmn/syntax.py
pybpmn/util.py
pybpmn/vis.py
pybpmn_parser-0.1.1.dist-info/LICENSE.txt
pybpmn_parser-0.1.1.dist-info/METADATA
pybpmn_parser-0.1.1.dist-info/WHEEL
pybpmn_parser-0.1.1.dist-info/top_level.txt
pybpmn_parser-0.1.1.dist-info/RECORD
