Metadata-Version: 2.1
Name: pybpmn-parser
Version: 0.1.1
Summary: Add a short description here!
Home-page: https://github.com/dwslab/pybpmn-parser/
Author: Bernhard Schäfer
Author-email: bernhard@informatik.uni-mannheim.de
License: MIT
Platform: any
Classifier: Development Status :: 4 - Beta
Classifier: Programming Language :: Python
Requires-Python: >=3.8
License-File: LICENSE.txt
Requires-Dist: yamlu
Requires-Dist: lxml
Requires-Dist: numpy
Requires-Dist: matplotlib
Requires-Dist: Pillow
Requires-Dist: joblib
Requires-Dist: tqdm
Provides-Extra: testing
Requires-Dist: setuptools ; extra == 'testing'
Requires-Dist: pytest ; extra == 'testing'
Requires-Dist: pytest-cov ; extra == 'testing'
